scrapple/__init__.py
scrapple/cmd.py
scrapple/commands/__init__.py
scrapple/commands/__init__.pyc
scrapple/commands/command.py
scrapple/commands/command.pyc
scrapple/commands/genconfig.py
scrapple/commands/genconfig.pyc
scrapple/commands/generate.py
scrapple/commands/generate.pyc
scrapple/commands/run.py
scrapple/commands/run.pyc
scrapple/commands/web.py
scrapple/commands/web.pyc
scrapple/commands/static/css/bootstrap-theme.css
scrapple/commands/static/css/bootstrap-theme.css.map
scrapple/commands/static/css/bootstrap-theme.min.css
scrapple/commands/static/css/bootstrap.css
scrapple/commands/static/css/bootstrap.css.map
scrapple/commands/static/css/bootstrap.min.css
scrapple/commands/static/fonts/glyphicons-halflings-regular.eot
scrapple/commands/static/fonts/glyphicons-halflings-regular.svg
scrapple/commands/static/fonts/glyphicons-halflings-regular.ttf
scrapple/commands/static/fonts/glyphicons-halflings-regular.woff
scrapple/commands/static/fonts/glyphicons-halflings-regular.woff2
scrapple/commands/static/js/bootstrap.js
scrapple/commands/static/js/bootstrap.min.js
scrapple/commands/static/js/jquery-1.11.2.min.js
scrapple/commands/templates/complete.html
scrapple/commands/templates/error.html
scrapple/commands/templates/home.html
scrapple/selectors/__init__.py
scrapple/selectors/css.py
scrapple/selectors/selector.py
scrapple/selectors/xpath.py
scrapple/templates/configs/crawler.txt
scrapple/templates/configs/scraper.txt
scrapple/templates/scripts/generate.txt
scrapple/utils/__init__.py
scrapple/utils/config.py
scrapple/utils/dynamicdispatch.py
scrapple/utils/exceptions.py
scrapple/utils/form.py
scrapple-0.2.6.dist-info/DESCRIPTION.rst
scrapple-0.2.6.dist-info/METADATA
scrapple-0.2.6.dist-info/RECORD
scrapple-0.2.6.dist-info/WHEEL
scrapple-0.2.6.dist-info/entry_points.txt
scrapple-0.2.6.dist-info/metadata.json
scrapple-0.2.6.dist-info/pbr.json
scrapple-0.2.6.dist-info/top_level.txt
