Metadata-Version: 1.1
Name: scrapple
Version: 0.2.6
Summary: A framework for creating web content extractors
Home-page: https://alexmathew.github.io/scrapple
Author: Alex Mathew
Author-email: alexmathew003@gmail.com
License: MIT
Keywords: scrapple,web,content,scraper,crawler
Platform: UNKNOWN
Classifier: Development Status :: 3 - Alpha
Classifier: Intended Audience :: Developers
Classifier: Intended Audience :: Science/Research
Classifier: License :: OSI Approved :: MIT License
Classifier: Natural Language :: English
Classifier: Programming Language :: Python :: 2.7
Classifier: Programming Language :: Python :: 3
Classifier: Programming Language :: Python :: 3.3
Classifier: Programming Language :: Python :: 3.4
Classifier: Topic :: Internet :: WWW/HTTP
Classifier: Topic :: Software Development :: Libraries :: Python Modules
Classifier: Topic :: Software Development :: Code Generators
